psychoanalyst/__init__.py
psychoanalyst/__main__.pyw
psychoanalyst/assets/cuy-128.ico
psychoanalyst/assets/cuy-doctor-128.ico
psychoanalyst/Base.py
psychoanalyst/common_data.py
psychoanalyst/Comparisons/__init__.py
psychoanalyst/Comparisons/categoria_interpretativa.py
psychoanalyst/Comparisons/estres.py
psychoanalyst/Comparisons/ryff.py
psychoanalyst/conversion_tables/Abstracción.csv
psychoanalyst/conversion_tables/Categoría interpretativa.csv
psychoanalyst/conversion_tables/Combinación A.csv
psychoanalyst/conversion_tables/Conversión T.csv
psychoanalyst/conversion_tables/DISC.csv
psychoanalyst/conversion_tables/Dominancia.csv
psychoanalyst/conversion_tables/Grado de bienestar psicológico.csv
psychoanalyst/conversion_tables/Vocabulario.csv
psychoanalyst/Exams/__init__.py
psychoanalyst/Exams/categoria_interpretativa.py
psychoanalyst/Exams/disc.py
psychoanalyst/Exams/estres.py
psychoanalyst/Exams/intereses_aptitude.py
psychoanalyst/Exams/ryff.py
psychoanalyst/interpretation_tools.py
psychoanalyst/loaders.py
psychoanalyst/savers.py
psychoanalyst/specifications.py
psychoanalyst-1.1.0.dist-info/entry_points.txt
psychoanalyst-1.1.0.dist-info/LICENSE
psychoanalyst-1.1.0.dist-info/LICENSE.rtf
psychoanalyst-1.1.0.dist-info/METADATA
psychoanalyst-1.1.0.dist-info/WHEEL
psychoanalyst-1.1.0.dist-info/RECORD
