Metadata-Version: 2.1
Name: psychoanalyst
Version: 1.1.0
Summary: Proyecto para análisis de exámenes psicológicos
License: Proprietary
Author: Ignacio de la Torre Arias
Author-email: ignaciodlta@gmail.com
Maintainer: Ignacio de la Torre Arias
Maintainer-email: ignaciodlta@gmail.com
Requires-Python: >=3.12,<3.13
Classifier: License :: Other/Proprietary License
Classifier: Programming Language :: Python :: 3
Classifier: Programming Language :: Python :: 3.12
Requires-Dist: dearpygui (>=1.11.1,<2.0.0)
Requires-Dist: matplotlib (>=3.9.1,<4.0.0)
Requires-Dist: pandas (>=2.2.2,<3.0.0)
